MANIFEST.in
README.md
setup.py
/Users/jonathanraiman/Desktop/Coding/python_packages/glove/glove/glove_inner.cpp
/Users/jonathanraiman/Desktop/Coding/python_packages/glove/glove/glove_inner.pyx
glove/__init__.py
glove/glove.py
glove/glove_inner.cpp
glove/glove_inner.pyx
glove.egg-info/PKG-INFO
glove.egg-info/SOURCES.txt
glove.egg-info/dependency_links.txt
glove.egg-info/not-zip-safe
glove.egg-info/requires.txt
glove.egg-info/top_level.txt